LICENSE
MANIFEST.in
README.rst
setup.py
rainbowrunners/__init__.py
rainbowrunners/djrunner.py
rainbowrunners/result.py
rainbowrunners/runner.py
rainbowrunners/utils.py
rainbowrunners.egg-info/PKG-INFO
rainbowrunners.egg-info/SOURCES.txt
rainbowrunners.egg-info/dependency_links.txt
rainbowrunners.egg-info/not-zip-safe
rainbowrunners.egg-info/top_level.txt