Metadata-Version: 1.1
Name: rainbowrunners
Version: 0.1
Summary: Awesome rainbow test runners
Home-page: http://gr1n.github.io/rainbowrunners/
Author: Nikita Grishko
Author-email: grin.minsk@gmail.com
License: MIT
Platform: UNKNOWN
Classifier: License :: OSI Approved :: MIT License
Classifier: Programming Language :: Python :: 2
Classifier: Programming Language :: Python :: 2.7
Classifier: Programming Language :: Python :: 3
Classifier: Programming Language :: Python :: 3.2
Classifier: Programming Language :: Python :: 3.3
Classifier: Programming Language :: Python :: Implementation :: CPython
